longbow/__init__.py
longbow/applications.py
longbow/configuration.py
longbow/entrypoints.py
longbow/exceptions.py
longbow/longbow
longbow/scheduling.py
longbow/shellwrappers.py
longbow/staging.py
longbow/apps/__init__.py
longbow/apps/amber.py
longbow/apps/charmm.py
longbow/apps/chemshell.py
longbow/apps/desmond.py
longbow/apps/gromacs.py
longbow/apps/lammps.py
longbow/apps/namd.py
longbow/schedulers/__init__.py
longbow/schedulers/lsf.py
longbow/schedulers/pbs.py
longbow/schedulers/sge.py
longbow/schedulers/slurm.py
longbow/schedulers/soge.py
longbow-1.5.4.dist-info/entry_points.txt
longbow-1.5.4.dist-info/licenses/LICENSE
longbow-1.5.4.dist-info/WHEEL
longbow-1.5.4.dist-info/METADATA
longbow-1.5.4.dist-info/RECORD
