Metadata-Version: 2.4
Name: Longbow
Version: 1.5.4
Summary: Biomolecular simulation remote job submission tool.
Keywords: aiida,plugin,gromacs,aiida-gromacs
Author-email: James Gebbie-Rayet <james.gebbie@stfc.ac.uk>
Requires-Python: >=3.4
Classifier: Development Status :: 5 - Production/Stable
Classifier: Environment :: Console
Classifier: Programming Language :: Python
Classifier: Topic :: Scientific/Engineering
Classifier: Topic :: Scientific/Engineering :: Bio-Informatics
Classifier: Topic :: Scientific/Engineering :: Chemistry
Classifier: Topic :: System :: Distributed Computing
Classifier: Topic :: Utilities
Classifier: Topic :: Software Development :: Libraries
Classifier: Operating System :: MacOS :: MacOS X
Classifier: Operating System :: POSIX :: Linux
Classifier: Operating System :: Unix
License-File: LICENSE
Requires-Dist: sphinx ; extra == "docs"
Requires-Dist: sphinx_rtd_theme ; extra == "docs"
Requires-Dist: sphinxcontrib-contentui ; extra == "docs"
Requires-Dist: sphinxcontrib-details-directive ; extra == "docs"
Requires-Dist: sphinx_copybutton ; extra == "docs"
Requires-Dist: furo ; extra == "docs"
Requires-Dist: markupsafe<2.1 ; extra == "docs"
Requires-Dist: pre-commit==3.7.1 ; extra == "pre-commit"
Requires-Dist: pylint==3.2.5 ; extra == "pre-commit"
Requires-Dist: pgtest==1.3.2 ; extra == "testing"
Requires-Dist: wheel==0.43.0 ; extra == "testing"
Requires-Dist: coverage[toml] ; extra == "testing"
Requires-Dist: pytest==8.2.2 ; extra == "testing"
Requires-Dist: pytest-cov==5.0.0 ; extra == "testing"
Requires-Dist: pytest-sugar==1.0.0 ; extra == "testing"
Project-URL: Source, https://github.com/HECBioSim/Longbow
Provides-Extra: docs
Provides-Extra: pre-commit
Provides-Extra: testing
